organization_profile_local/__init__.py
organization_profile_local/organization_profile_constants.py
organization_profile_local/organization_profiles_local.py
organization_profile_local-0.0.17.dist-info/METADATA
organization_profile_local-0.0.17.dist-info/WHEEL
organization_profile_local-0.0.17.dist-info/top_level.txt
organization_profile_local-0.0.17.dist-info/RECORD
