Metadata-Version: 2.1
Name: organization-profile-local
Version: 0.0.17
Summary: PyPI Package for Circles organization-profile-local Python
Home-page: https://github.com/circles-zone/organization-profile-local-python-package
Author: Circles
Author-email: info@circlez.ai
Classifier: Programming Language :: Python :: 3
Classifier: License :: Other/Proprietary License
Classifier: Operating System :: OS Independent
Requires-Dist: logger-local
Requires-Dist: database-mysql-local
